changedifferently/__init__.py
changedifferently/py.typed
changedifferently/version/VERSION
changedifferently/version/__init__.py
changedifferently/version/py.typed
changedifferently-1.0.0a1.dist-info/LICENSE
changedifferently-1.0.0a1.dist-info/METADATA
changedifferently-1.0.0a1.dist-info/WHEEL
changedifferently-1.0.0a1.dist-info/top_level.txt
changedifferently-1.0.0a1.dist-info/RECORD
